{
  "type": "template",
  "altText": "this is a carousel template",
  "template": {
    "type": "carousel",
    "columns": [
      {
        "thumbnailImageUrl": "",
        "imageBackgroundColor": "#FFFFFF",
        "title": "",
        "text": "",
        "defaultAction": {
          "type": "uri",
          "label": "View detail",
          "uri": ""
        },
        "actions": [
          {
            "type": "postback",
            "label": "",
            "data": "action=triggerReply&triggerModuleId="
          }
        ]
      }
    ],
    "imageAspectRatio": "rectangle",
    "imageSize": "cover"
  }
}